Workbook

Sheet Model Setup
A1: Foresight Generated Market Model
A3: Field | B3: Value
A4: Forecast name | B4: Hemaris Switzerland Forecast
A5: Product | B5: Hemaris
A6: Country | B6: Switzerland
A7: Currency | B7: CHF
A8: Forecast period | B8: 2022-2031
A9: External market source | B9: Client-owned syndicated market data
A10: Internal sales source | B10: Internal sales data
A11: Granularity | B11: SKU / strength / pack
A12: Forecast method | B12: Historical trend + events
A13: Products | B13: 3
A14: Competitors | B14: 4
A15: SKUs | B15: 5
A16: Output | B16: Baseline vs Event-adjusted
A17: Generated | B17: 2026-07-24T08:08:16.130Z

Sheet Market Inputs
A1: Metric | B1: Unit | C1: 2022 | D1: 2023 | E1: 2024 | F1: 2025 | G1: 2026 | H1: 2027 | I1: 2028 | J1: 2029 | K1: 2030 | L1: 2031
A2: Baseline market volume | B2: units | C2: 1000000
A3: Annual market growth | B3: % | C3: -0.02 | D3: -0.02 | E3: -0.02 | F3: -0.02 | G3: -0.02 | H3: -0.02 | I3: -0.02 | J3: -0.02 | K3: -0.02 | L3: -0.02
A4: Product share | B4: % | C4: 0.2 | D4: 0.2 | E4: 0.2 | F4: 0.2 | G4: 0.2 | H4: 0.2 | I4: 0.2 | J4: 0.2 | K4: 0.2 | L4: 0.2
A5: Price per unit | B5: CHF | C5: 1 | D5: 1 | E5: 1 | F5: 1 | G5: 1 | H5: 1 | I5: 1 | J5: 1 | K5: 1 | L5: 1
A6: Volume event impact | B6: % | C6: 0 | D6: 0 | E6: 0 | F6: 0 | G6: 0 | H6: 0 | I6: 0 | J6: 0 | K6: 0 | L6: 0
A7: Price event impact | B7: % | C7: 0 | D7: 0 | E7: 0 | F7: 0 | G7: 0 | H7: 0 | I7: 0 | J7: 0 | K7: 0 | L7: 0
A8: Event probability | B8: % | C8: 1 | D8: 1 | E8: 1 | F8: 1 | G8: 1 | H8: 1 | I8: 1 | J8: 1 | K8: 1 | L8: 1
A9: COGS per unit | B9: CHF | C9: 0.35 | D9: 0.35 | E9: 0.35 | F9: 0.35 | G9: 0.35 | H9: 0.35 | I9: 0.35 | J9: 0.35 | K9: 0.35 | L9: 0.35
A10: Service fee | B10: % | C10: 0.025 | D10: 0.025 | E10: 0.025 | F10: 0.025 | G10: 0.025 | H10: 0.025 | I10: 0.025 | J10: 0.025 | K10: 0.025 | L10: 0.025
A11: Supply fee | B11: % | C11: 0.05 | D11: 0.05 | E11: 0.05 | F11: 0.05 | G11: 0.05 | H11: 0.05 | I11: 0.05 | J11: 0.05 | K11: 0.05 | L11: 0.05

Sheet Forecast Outputs
A1: Metric | B1: Unit | C1: 2022 | D1: 2023 | E1: 2024 | F1: 2025 | G1: 2026 | H1: 2027 | I1: 2028 | J1: 2029 | K1: 2030 | L1: 2031
A2: Baseline product volume | B2: units | C2: ='Market Inputs'!C2*'Market Inputs'!C4 -> 0 | D2: =C2*(1+'Market Inputs'!D3) -> 0 | E2: =D2*(1+'Market Inputs'!E3) -> 0 | F2: =E2*(1+'Market Inputs'!F3) -> 0 | G2: =F2*(1+'Market Inputs'!G3) -> 0 | H2: =G2*(1+'Market Inputs'!H3) -> 0 | I2: =H2*(1+'Market Inputs'!I3) -> 0 | J2: =I2*(1+'Market Inputs'!J3) -> 0 | K2: =J2*(1+'Market Inputs'!K3) -> 0 | L2: =K2*(1+'Market Inputs'!L3) -> 0
A3: Event-adjusted volume | B3: units | C3: =C2*(1+'Market Inputs'!C6*'Market Inputs'!C8) -> 0 | D3: =D2*(1+'Market Inputs'!D6*'Market Inputs'!D8) -> 0 | E3: =E2*(1+'Market Inputs'!E6*'Market Inputs'!E8) -> 0 | F3: =F2*(1+'Market Inputs'!F6*'Market Inputs'!F8) -> 0 | G3: =G2*(1+'Market Inputs'!G6*'Market Inputs'!G8) -> 0 | H3: =H2*(1+'Market Inputs'!H6*'Market Inputs'!H8) -> 0 | I3: =I2*(1+'Market Inputs'!I6*'Market Inputs'!I8) -> 0 | J3: =J2*(1+'Market Inputs'!J6*'Market Inputs'!J8) -> 0 | ... L3: =L2*(1+'Market Inputs'!L6*'Market Inputs'!L8) -> 0
A4: Baseline revenue | B4: CHF | C4: =C2*'Market Inputs'!C5 -> 0 | D4: =D2*'Market Inputs'!D5 -> 0 | E4: =E2*'Market Inputs'!E5 -> 0 | F4: =F2*'Market Inputs'!F5 -> 0 | G4: =G2*'Market Inputs'!G5 -> 0 | H4: =H2*'Market Inputs'!H5 -> 0 | I4: =I2*'Market Inputs'!I5 -> 0 | J4: =J2*'Market Inputs'!J5 -> 0 | ... L4: =L2*'Market Inputs'!L5 -> 0
A5: Event-adjusted revenue | B5: CHF | C5: =C3*'Market Inputs'!C5*(1+'Market Inputs'!C7*'Market Inputs'!C8) -> 0 | D5: =D3*'Market Inputs'!D5*(1+'Market Inputs'!D7*'Market Inputs'!D8) -> 0 | E5: =E3*'Market Inputs'!E5*(1+'Market Inputs'!E7*'Market Inputs'!E8) -> 0 | F5: =F3*'Market Inputs'!F5*(1+'Market Inputs'!F7*'Market Inputs'!F8) -> 0 | G5: =G3*'Market Inputs'!G5*(1+'Market Inputs'!G7*'Market Inputs'!G8) -> 0 | H5: =H3*'Market Inputs'!H5*(1+'Market Inputs'!H7*'Market Inputs'!H8) -> 0 | I5: =I3*'Market Inputs'!I5*(1+'Market Inputs'!I7*'Market Inputs'!I8) -> 0 | J5: =J3*'Market Inputs'!J5*(1+'Market Inputs'!J7*'Market Inputs'!J8) -> 0 | ... L5: =L3*'Market Inputs'!L5*(1+'Market Inputs'!L7*'Market Inputs'!L8) -> 0
A6: Gross margin | B6: CHF | C6: =C5-C3*'Market Inputs'!C9-C5*('Market Inputs'!C10+'Market Inputs'!C11) -> 0 | D6: =D5-D3*'Market Inputs'!D9-D5*('Market Inputs'!D10+'Market Inputs'!D11) -> 0 | E6: =E5-E3*'Market Inputs'!E9-E5*('Market Inputs'!E10+'Market Inputs'!E11) -> 0 | F6: =F5-F3*'Market Inputs'!F9-F5*('Market Inputs'!F10+'Market Inputs'!F11) -> 0 | G6: =G5-G3*'Market Inputs'!G9-G5*('Market Inputs'!G10+'Market Inputs'!G11) -> 0 | H6: =H5-H3*'Market Inputs'!H9-H5*('Market Inputs'!H10+'Market Inputs'!H11) -> 0 | I6: =I5-I3*'Market Inputs'!I9-I5*('Market Inputs'!I10+'Market Inputs'!I11) -> 0 | J6: =J5-J3*'Market Inputs'!J9-J5*('Market Inputs'!J10+'Market Inputs'!J11) -> 0 | ... L6: =L5-L3*'Market Inputs'!L9-L5*('Market Inputs'!L10+'Market Inputs'!L11) -> 0
A7: Gross margin % | B7: % | C7: =IFERROR(C6/C5,0) -> 0 | D7: =IFERROR(D6/D5,0) -> 0 | E7: =IFERROR(E6/E5,0) -> 0 | F7: =IFERROR(F6/F5,0) -> 0 | G7: =IFERROR(G6/G5,0) -> 0 | H7: =IFERROR(H6/H5,0) -> 0 | I7: =IFERROR(I6/I5,0) -> 0 | J7: =IFERROR(J6/J5,0) -> 0 | ... L7: =IFERROR(L6/L5,0) -> 0

Sheet SKU Structure
A1: SKU | B1: Strength | C1: Pack | D1: Volume share | E1: Price | F1: COGS / unit
A2: SKU 1 | D2: 0.2
A3: SKU 2
A4: SKU 3
A5: SKU 4
A6: SKU 5

Sheet Validation
A1: Status | B1: Check | C1: Detail
A2: Passed | B2: Forecast period | C2: 2022-2031
A3: Review | B3: Historical data | C3: Populate client-owned market and internal sales history
A4: Review | B4: Events | C4: Set event impact, probability, and timing
A5: Passed | B5: Financial conversion | C5: Revenue, COGS, fee, and gross-margin formulas included
